{
	"display": {
		"title": {"text":"Mario"},
		"description": {"text":""},
		"icon": {
			"item": "minecraft:player_head",
			"nbt": "{SkullOwner:{Id:[I;-1735030730,1317359197,-1675596060,1730408962],Properties:{textures:[{Value:\"eyJ0ZXh0dXJlcyI6eyJTS0lOIjp7InVybCI6Imh0dHA6Ly90ZXh0dXJlcy5taW5lY3JhZnQubmV0L3RleHR1cmUvNmY3ZWI3NWU1NTQyY2M0OTM3YWFhZDViYjg2NTczOTNlYWYwMjY1MDA2ZWFjMWRjOTY2OTFmMzJlMTY0MzcifX19\"}]}}}"
		},
        "show_toast": false,
        "announce_to_chat": false,
		"frame": "task"
	},
	"parent": "kitpvp:played/witherskeleton",
	"criteria": {
		"welcome": {
			"trigger": "minecraft:impossible"
		}
	}
}
